MANIFEST.in
README.md
setup.py
sieve_git_pushdeploy/__init__.py
sieve_git_pushdeploy/hooks.py
sieve_git_pushdeploy/sieve.conf.example
sieve_git_pushdeploy.egg-info/PKG-INFO
sieve_git_pushdeploy.egg-info/SOURCES.txt
sieve_git_pushdeploy.egg-info/dependency_links.txt
sieve_git_pushdeploy.egg-info/entry_points.txt
sieve_git_pushdeploy.egg-info/requires.txt
sieve_git_pushdeploy.egg-info/top_level.txt