Metadata-Version: 1.1
Name: sieve-git-pushdeploy
Version: 0.4.0
Summary: Push a sieve script to your mailserver and have it applied automatically.
Home-page: https://github.com/mheistermann/sieve-git-pushdeploy
Author: Martin Heistermann
Author-email: sieve-git-pushdeploy@mheistermann.de
License: GPLv3+
Keywords: git sieve pushdeployment
Platform: UNKNOWN
Classifier: Development Status :: 3 - Alpha
Classifier: Intended Audience :: System Administrators
Classifier: License :: OSI Approved :: GNU General Public License v3 or later (GPLv3+)
Classifier: Programming Language :: Python :: 3 :: Only
